README.rst
setup.cfg
setup.py
pipcheck/__init__.py
pipcheck/__main__.py
pipcheck/arg_parser.py
pipcheck/checker.py
pipcheck/clients.py
pipcheck/constants.py
pipcheck/exceptions.py
pipcheck/update.py
pipcheck.egg-info/PKG-INFO
pipcheck.egg-info/SOURCES.txt
pipcheck.egg-info/dependency_links.txt
pipcheck.egg-info/entry_points.txt
pipcheck.egg-info/requires.txt
pipcheck.egg-info/top_level.txt