Metadata-Version: 1.1
Name: pipcheck
Version: 1.3.1
Summary: Environment package update checker
Home-page: https://github.com/mikejarrett/pipcheck
Author: Mike Jarrett
Author-email: UNKNOWN
License: UNKNOWN
Download-URL: https://github.com/mikejarrett/pipcheck
Platform: UNKNOWN
Classifier: Development Status :: 5 - Production/Stable
Classifier: Intended Audience :: End Users/Desktop
Classifier: Programming Language :: Python :: 2.6
Classifier: Programming Language :: Python :: 2.7
Classifier: Programming Language :: Python :: 3
Classifier: Programming Language :: Python :: 3.0
Classifier: Programming Language :: Python :: 3.1
Classifier: Programming Language :: Python :: 3.4
